rwc/__init__.py
rwc/__main__.py
rwc/cli.py
rwc/render.py
rwc/formats/__init__.py
rwc/formats/html.py
rwc/formats/markdown.py
rwc/formats/restructuredtext.py
rwc-0.2.0.dist-info/LICENSE
rwc-0.2.0.dist-info/METADATA
rwc-0.2.0.dist-info/WHEEL
rwc-0.2.0.dist-info/entry_points.txt
rwc-0.2.0.dist-info/top_level.txt
rwc-0.2.0.dist-info/RECORD
